Workbook

Sheet Dashboard
A1: DONKEY MARBLE RACING — FINANCIAL FORECAST DASHBOARD
A2: 60-Month Business Plan & Revenue Projections
A4: KEY ASSUMPTIONS | F4: REVENUE STREAMS
A5: Launch Platform | B5: iOS + Android (simultaneous) | F5: Coin Packs (IAP) | G5: $0.99 - $24.99 | H5: Primary
A6: Apple App Store Fee | B6: 30% (15% under Small Business Program < $1M/yr) | F6: Season Pass — Premium | G6: $9.99/season | H6: Recurring
A7: Google Play Fee | B7: 15% (first $1M/yr), then 30% | F7: Season Pass — Plus | G7: $24.99/season | H7: Recurring
A8: Avg. Conversion Rate (Free→Paid) | B8: 3-5% (industry avg for casual games) | F8: Future: Ad Revenue (rewarded) | G8: eCPM $10-30 | H8: Supplemental
A9: Avg. Revenue Per Paying User (ARPPU) | B9: $8-15/month | F9: Future: Cosmetic Store | G9: $0.99 - $4.99 | H9: Supplemental
A10: Monthly Churn Rate | B10: 8-12% for paying users | F10: Future: Tournament Entry | G10: Coin-gated | H10: Engagement
A11: User Acquisition Cost (est.) | B11: $1.50-3.00 per install
A12: Organic Install Rate | B12: 40% of total installs
A13: Season Length | B13: 30 days
A14: Daily Active User Rate | B14: 25-35% of total installs

Sheet Pricing Matrix
A1: PRICING MATRIX — REVENUE AFTER APP STORE FEES
A3: A. CURRENT IN-APP PURCHASES
A4: Product | B4: Retail Price | C4: Coins Given | D4: Coins/Dollar | E4: Apple 30% You Receive | F4: Apple 15% (Small Biz) You Receive | G4: Google 15% You Receive | H4: Google 30% You Receive | I4: Best Case (15% fee) | J4: Worst Case (30% fee)
A5: Starter Pack | B5: 0.99 | C5: 1000 | D5: 1010 | E5: 0.69 | F5: 0.84 | G5: 0.84 | H5: 0.69 | I5: 0.84 | J5: 0.69
A6: Popular Pack | B6: 4.99 | C6: 6000 | D6: 1202 | E6: 3.49 | F6: 4.24 | G6: 4.24 | H6: 3.49 | I6: 4.24 | J6: 3.49
A7: Big Spender | B7: 9.99 | C7: 15000 | D7: 1502 | E7: 6.99 | F7: 8.49 | G7: 8.49 | H7: 6.99 | I7: 8.49 | J7: 6.99
A8: Whale Pack | B8: 24.99 | C8: 40000 | D8: 1601 | E8: 17.49 | F8: 21.24 | G8: 21.24 | H8: 17.49 | I8: 21.24 | J8: 17.49
A9: Season Pass — Premium | B9: 9.99 | C9: — | D9: N/A | E9: 6.99 | F9: 8.49 | G9: 8.49 | H9: 6.99 | I9: 8.49 | J9: 6.99
A10: Season Pass — Plus | B10: 24.99 | C10: — | D10: N/A | E10: 17.49 | F10: 21.24 | G10: 21.24 | H10: 17.49 | I10: 21.24 | J10: 17.49
A13: B. APP STORE FEE COMPARISON
A14: Scenario | B14: Fee Rate | C14: On $0.99 | D14: On $4.99 | E14: On $9.99 | F14: On $24.99 | G14: On $100 Revenue | H14: On $1,000 Revenue | I14: On $10,000 Revenue | J14: Annual Impact
A15: Apple Standard | B15: 0.3 | C15: 0.3 | D15: 1.5 | E15: 3 | F15: 7.5 | G15: 30 | H15: 300 | I15: 3000 | J15: 150000
A16: Apple Small Business (<$1M) | B16: 0.15 | C16: 0.15 | D16: 0.75 | E16: 1.5 | F16: 3.75 | G16: 15 | H16: 150 | I16: 1500 | J16: 75000
A17: Google Play (first $1M) | B17: 0.15 | C17: 0.15 | D17: 0.75 | E17: 1.5 | F17: 3.75 | G17: 15 | H17: 150 | I17: 1500 | J17: 75000
A18: Google Play (over $1M) | B18: 0.3 | C18: 0.3 | D18: 1.5 | E18: 3 | F18: 7.5 | G18: 30 | H18: 300 | I18: 3000 | J18: 150000
A21: C. UNITS NEEDED TO REACH REVENUE TARGETS (After 15% Fee)
A22: Product | B22: Net Per Unit | C22: Units for $1K/mo | D22: Units for $5K/mo | E22: Units for $10K/mo | F22: Units for $50K/mo
A23: Starter Pack | B23: 0.84 | C23: 1191 | D23: 5953 | E23: 11905 | F23: 59524
A24: Popular Pack | B24: 4.24 | C24: 236 | D24: 1180 | E24: 2359 | F24: 11793
A25: Big Spender | B25: 8.49 | C25: 118 | D25: 589 | E25: 1178 | F25: 5890
A26: Whale Pack | B26: 21.24 | C26: 48 | D26: 236 | E26: 471 | F26: 2355
A27: Season Pass — Premium | B27: 8.49 | C27: 118 | D27: 589 | E27: 1178 | F27: 5890
A28: Season Pass — Plus | B28: 21.24 | C28: 48 | D28: 236 | E28: 471 | F28: 2355

Sheet 60-Month Forecast
A1: 60-MONTH REVENUE & USER FORECAST
A3: EDITABLE INPUTS (Change yellow cells to update forecast)
A4: Launch Month Installs | B4: 2000
A5: Monthly Install Growth Rate | B5: 0.12
A6: Install Growth Decay (per month) | B6: 0.003
A7: Free-to-Paid Conversion Rate | B7: 0.04
A8: Avg Revenue Per Paying User (ARPPU) | B8: 7.5
A9: Monthly Paying User Churn Rate | B9: 0.1
A10: Monthly Free User Churn Rate | B10: 0.15
A11: ARPPU Annual Growth Rate | B11: 0.05
A12: App Store Fee Rate | B12: 0.15
A13: Monthly Server/Infra Cost | B13: 200
A14: Monthly Marketing Spend | B14: 500
A15: Cost Per Install (paid) | B15: 2
A16: Organic Install % | B16: 0.4
A18: MONTHLY FORECAST
A19: Month | B19: New Installs | C19: Cumulative Installs | D19: Total Free Users | E19: Total Paying Users | F19: Total Active Users | G19: New Conversions | H19: Gross Revenue | I19: App Store Fees | J19: Net Revenue | K19: Server Costs | L19: Marketing Spend | M19: UA Cost (Paid Installs) | N19: Total Costs | O19: Net Profit/Loss | P19: Cumulative Profit/Loss | Q19: ARPU (All Users) | R19: LTV Est. (Paying) | S19: Paying User %
A20: 1 | B20: =B4 | C20: =B20 | D20: =ROUND(B20*(1-B7),0) | E20: =ROUND(B20*B7,0) | F20: =D20+E20 | G20: =ROUND(B20*B7,0) | H20: =ROUND(E20*B8*(1+B11)^(INT((1-1)/12)),2) | I20: =ROUND(H20*B12,2) | J20: =H20-I20 | K20: =ROUND(B13*(1+F20/10000*0.5),2) | L20: =B14 | M20: =ROUND(B20*(1-B16)*B15,2) | N20: =K20+L20+M20 | O20: =J20-N20 | P20: =O20 | Q20: =IF(F20>0,ROUND(J20/F20,2),0) | R20: =IF(B9>0,ROUND(B8*(1-B12)/B9*(1+B11)^(INT((1-1)/12)),2),0) | S20: =IF(F20>0,E20/F20,0)
A21: 2 | B21: =ROUND(B4*(1+B5-B6*2)^(2-1),0) | C21: =C20+B21 | D21: =ROUND(D20*(1-B10)+B21*(1-B7),0) | E21: =ROUND(E20*(1-B9)+G21,0) | F21: =D21+E21 | G21: =ROUND(B21*B7+D20*0.005,0) | H21: =ROUND(E21*B8*(1+B11)^(INT((2-1)/12)),2) | I21: =ROUND(H21*B12,2) | J21: =H21-I21 | K21: =ROUND(B13*(1+F21/10000*0.5),2) | L21: =B14 | M21: =ROUND(B21*(1-B16)*B15,2) | N21: =K21+L21+M21 | O21: =J21-N21 | P21: =P20+O21 | Q21: =IF(F21>0,ROUND(J21/F21,2),0) | R21: =IF(B9>0,ROUND(B8*(1-B12)/B9*(1+B11)^(INT((2-1)/12)),2),0) | S21: =IF(F21>0,E21/F21,0)
A22: 3 | B22: =ROUND(B4*(1+B5-B6*3)^(3-1),0) | C22: =C21+B22 | D22: =ROUND(D21*(1-B10)+B22*(1-B7),0) | E22: =ROUND(E21*(1-B9)+G22,0) | F22: =D22+E22 | G22: =ROUND(B22*B7+D21*0.005,0) | H22: =ROUND(E22*B8*(1+B11)^(INT((3-1)/12)),2) | I22: =ROUND(H22*B12,2) | J22: =H22-I22 | K22: =ROUND(B13*(1+F22/10000*0.5),2) | L22: =B14 | M22: =ROUND(B22*(1-B16)*B15,2) | N22: =K22+L22+M22 | O22: =J22-N22 | P22: =P21+O22 | Q22: =IF(F22>0,ROUND(J22/F22,2),0) | R22: =IF(B9>0,ROUND(B8*(1-B12)/B9*(1+B11)^(INT((3-1)/12)),2),0) | S22: =IF(F22>0,E22/F22,0)
A23: 4 | B23: =ROUND(B4*(1+B5-B6*4)^(4-1),0) | C23: =C22+B23 | D23: =ROUND(D22*(1-B10)+B23*(1-B7),0) | E23: =ROUND(E22*(1-B9)+G23,0) | F23: =D23+E23 | G23: =ROUND(B23*B7+D22*0.005,0) | H23: =ROUND(E23*B8*(1+B11)^(INT((4-1)/12)),2) | I23: =ROUND(H23*B12,2) | J23: =H23-I23 | K23: =ROUND(B13*(1+F23/10000*0.5),2) | L23: =B14 | M23: =ROUND(B23*(1-B16)*B15,2) | N23: =K23+L23+M23 | O23: =J23-N23 | P23: =P22+O23 | Q23: =IF(F23>0,ROUND(J23/F23,2),0) | R23: =IF(B9>0,ROUND(B8*(1-B12)/B9*(1+B11)^(INT((4-1)/12)),2),0) | S23: =IF(F23>0,E23/F23,0)
A24: 5 | B24: =ROUND(B4*(1+B5-B6*5)^(5-1),0) | C24: =C23+B24 | D24: =ROUND(D23*(1-B10)+B24*(1-B7),0) | E24: =ROUND(E23*(1-B9)+G24,0) | F24: =D24+E24 | G24: =ROUND(B24*B7+D23*0.005,0) | H24: =ROUND(E24*B8*(1+B11)^(INT((5-1)/12)),2) | I24: =ROUND(H24*B12,2) | J24: =H24-I24 | K24: =ROUND(B13*(1+F24/10000*0.5),2) | L24: =B14 | M24: =ROUND(B24*(1-B16)*B15,2) | N24: =K24+L24+M24 | O24: =J24-N24 | P24: =P23+O24 | Q24: =IF(F24>0,ROUND(J24/F24,2),0) | R24: =IF(B9>0,ROUND(B8*(1-B12)/B9*(1+B11)^(INT((5-1)/12)),2),0) | S24: =IF(F24>0,E24/F24,0)
A25: 6 | B25: =ROUND(B4*(1+B5-B6*6)^(6-1),0) | C25: =C24+B25 | D25: =ROUND(D24*(1-B10)+B25*(1-B7),0) | E25: =ROUND(E24*(1-B9)+G25,0) | F25: =D25+E25 | G25: =ROUND(B25*B7+D24*0.005,0) | H25: =ROUND(E25*B8*(1+B11)^(INT((6-1)/12)),2) | I25: =ROUND(H25*B12,2) | J25: =H25-I25 | K25: =ROUND(B13*(1+F25/10000*0.5),2) | L25: =B14 | M25: =ROUND(B25*(1-B16)*B15,2) | N25: =K25+L25+M25 | O25: =J25-N25 | P25: =P24+O25 | Q25: =IF(F25>0,ROUND(J25/F25,2),0) | R25: =IF(B9>0,ROUND(B8*(1-B12)/B9*(1+B11)^(INT((6-1)/12)),2),0) | S25: =IF(F25>0,E25/F25,0)
A26: 7 | B26: =ROUND(B4*(1+B5-B6*7)^(7-1),0) | C26: =C25+B26 | D26: =ROUND(D25*(1-B10)+B26*(1-B7),0) | E26: =ROUND(E25*(1-B9)+G26,0) | F26: =D26+E26 | G26: =ROUND(B26*B7+D25*0.005,0) | H26: =ROUND(E26*B8*(1+B11)^(INT((7-1)/12)),2) | I26: =ROUND(H26*B12,2) | J26: =H26-I26 | K26: =ROUND(B13*(1+F26/10000*0.5),2) | L26: =B14 | M26: =ROUND(B26*(1-B16)*B15,2) | N26: =K26+L26+M26 | O26: =J26-N26 | P26: =P25+O26 | Q26: =IF(F26>0,ROUND(J26/F26,2),0) | R26: =IF(B9>0,ROUND(B8*(1-B12)/B9*(1+B11)^(INT((7-1)/12)),2),0) | S26: =IF(F26>0,E26/F26,0)
A27: 8 | B27: =ROUND(B4*(1+B5-B6*8)^(8-1),0) | C27: =C26+B27 | D27: =ROUND(D26*(1-B10)+B27*(1-B7),0) | E27: =ROUND(E26*(1-B9)+G27,0) | F27: =D27+E27 | G27: =ROUND(B27*B7+D26*0.005,0) | H27: =ROUND(E27*B8*(1+B11)^(INT((8-1)/12)),2) | I27: =ROUND(H27*B12,2) | J27: =H27-I27 | K27: =ROUND(B13*(1+F27/10000*0.5),2) | L27: =B14 | M27: =ROUND(B27*(1-B16)*B15,2) | N27: =K27+L27+M27 | O27: =J27-N27 | P27: =P26+O27 | Q27: =IF(F27>0,ROUND(J27/F27,2),0) | R27: =IF(B9>0,ROUND(B8*(1-B12)/B9*(1+B11)^(INT((8-1)/12)),2),0) | S27: =IF(F27>0,E27/F27,0)
A28: 9 | B28: =ROUND(B4*(1+B5-B6*9)^(9-1),0) | C28: =C27+B28 | D28: =ROUND(D27*(1-B10)+B28*(1-B7),0) | E28: =ROUND(E27*(1-B9)+G28,0) | F28: =D28+E28 | G28: =ROUND(B28*B7+D27*0.005,0) | H28: =ROUND(E28*B8*(1+B11)^(INT((9-1)/12)),2) | I28: =ROUND(H28*B12,2) | J28: =H28-I28 | K28: =ROUND(B13*(1+F28/10000*0.5),2) | L28: =B14 | M28: =ROUND(B28*(1-B16)*B15,2) | N28: =K28+L28+M28 | O28: =J28-N28 | P28: =P27+O28 | Q28: =IF(F28>0,ROUND(J28/F28,2),0) | R28: =IF(B9>0,ROUND(B8*(1-B12)/B9*(1+B11)^(INT((9-1)/12)),2),0) | S28: =IF(F28>0,E28/F28,0)
A29: 10 | B29: =ROUND(B4*(1+B5-B6*10)^(10-1),0) | C29: =C28+B29 | D29: =ROUND(D28*(1-B10)+B29*(1-B7),0) | E29: =ROUND(E28*(1-B9)+G29,0) | F29: =D29+E29 | G29: =ROUND(B29*B7+D28*0.005,0) | H29: =ROUND(E29*B8*(1+B11)^(INT((10-1)/12)),2) | I29: =ROUND(H29*B12,2) | J29: =H29-I29 | K29: =ROUND(B13*(1+F29/10000*0.5),2) | L29: =B14 | M29: =ROUND(B29*(1-B16)*B15,2) | N29: =K29+L29+M29 | O29: =J29-N29 | P29: =P28+O29 | Q29: =IF(F29>0,ROUND(J29/F29,2),0) | R29: =IF(B9>0,ROUND(B8*(1-B12)/B9*(1+B11)^(INT((10-1)/12)),2),0) | S29: =IF(F29>0,E29/F29,0)
A30: 11 | B30: =ROUND(B4*(1+B5-B6*11)^(11-1),0) | C30: =C29+B30 | D30: =ROUND(D29*(1-B10)+B30*(1-B7),0) | E30: =ROUND(E29*(1-B9)+G30,0) | F30: =D30+E30 | G30: =ROUND(B30*B7+D29*0.005,0) | H30: =ROUND(E30*B8*(1+B11)^(INT((11-1)/12)),2) | I30: =ROUND(H30*B12,2) | J30: =H30-I30 | K30: =ROUND(B13*(1+F30/10000*0.5),2) | L30: =B14 | M30: =ROUND(B30*(1-B16)*B15,2) | N30: =K30+L30+M30 | O30: =J30-N30 | P30: =P29+O30 | Q30: =IF(F30>0,ROUND(J30/F30,2),0) | R30: =IF(B9>0,ROUND(B8*(1-B12)/B9*(1+B11)^(INT((11-1)/12)),2),0) | S30: =IF(F30>0,E30/F30,0)
A31: 12 | B31: =ROUND(B4*(1+B5-B6*12)^(12-1),0) | C31: =C30+B31 | D31: =ROUND(D30*(1-B10)+B31*(1-B7),0) | E31: =ROUND(E30*(1-B9)+G31,0) | F31: =D31+E31 | G31: =ROUND(B31*B7+D30*0.005,0) | H31: =ROUND(E31*B8*(1+B11)^(INT((12-1)/12)),2) | I31: =ROUND(H31*B12,2) | J31: =H31-I31 | K31: =ROUND(B13*(1+F31/10000*0.5),2) | L31: =B14 | M31: =ROUND(B31*(1-B16)*B15,2) | N31: =K31+L31+M31 | O31: =J31-N31 | P31: =P30+O31 | Q31: =IF(F31>0,ROUND(J31/F31,2),0) | R31: =IF(B9>0,ROUND(B8*(1-B12)/B9*(1+B11)^(INT((12-1)/12)),2),0) | S31: =IF(F31>0,E31/F31,0)
A32: 13 | B32: =ROUND(B4*(1+B5-B6*13)^(13-1),0) | C32: =C31+B32 | D32: =ROUND(D31*(1-B10)+B32*(1-B7),0) | E32: =ROUND(E31*(1-B9)+G32,0) | F32: =D32+E32 | G32: =ROUND(B32*B7+D31*0.005,0) | H32: =ROUND(E32*B8*(1+B11)^(INT((13-1)/12)),2) | I32: =ROUND(H32*B12,2) | J32: =H32-I32 | K32: =ROUND(B13*(1+F32/10000*0.5),2) | L32: =B14 | M32: =ROUND(B32*(1-B16)*B15,2) | N32: =K32+L32+M32 | O32: =J32-N32 | P32: =P31+O32 | Q32: =IF(F32>0,ROUND(J32/F32,2),0) | R32: =IF(B9>0,ROUND(B8*(1-B12)/B9*(1+B11)^(INT((13-1)/12)),2),0) | S32: =IF(F32>0,E32/F32,0)
A33: 14 | B33: =ROUND(B4*(1+B5-B6*14)^(14-1),0) | C33: =C32+B33 | D33: =ROUND(D32*(1-B10)+B33*(1-B7),0) | E33: =ROUND(E32*(1-B9)+G33,0) | F33: =D33+E33 | G33: =ROUND(B33*B7+D32*0.005,0) | H33: =ROUND(E33*B8*(1+B11)^(INT((14-1)/12)),2) | I33: =ROUND(H33*B12,2) | J33: =H33-I33 | K33: =ROUND(B13*(1+F33/10000*0.5),2) | L33: =B14 | M33: =ROUND(B33*(1-B16)*B15,2) | N33: =K33+L33+M33 | O33: =J33-N33 | P33: =P32+O33 | Q33: =IF(F33>0,ROUND(J33/F33,2),0) | R33: =IF(B9>0,ROUND(B8*(1-B12)/B9*(1+B11)^(INT((14-1)/12)),2),0) | S33: =IF(F33>0,E33/F33,0)
A34: 15 | B34: =ROUND(B4*(1+B5-B6*15)^(15-1),0) | C34: =C33+B34 | D34: =ROUND(D33*(1-B10)+B34*(1-B7),0) | E34: =ROUND(E33*(1-B9)+G34,0) | F34: =D34+E34 | G34: =ROUND(B34*B7+D33*0.005,0) | H34: =ROUND(E34*B8*(1+B11)^(INT((15-1)/12)),2) | I34: =ROUND(H34*B12,2) | J34: =H34-I34 | K34: =ROUND(B13*(1+F34/10000*0.5),2) | L34: =B14 | M34: =ROUND(B34*(1-B16)*B15,2) | N34: =K34+L34+M34 | O34: =J34-N34 | P34: =P33+O34 | Q34: =IF(F34>0,ROUND(J34/F34,2),0) | R34: =IF(B9>0,ROUND(B8*(1-B12)/B9*(1+B11)^(INT((15-1)/12)),2),0) | S34: =IF(F34>0,E34/F34,0)
A35: 16 | B35: =ROUND(B4*(1+B5-B6*16)^(16-1),0) | C35: =C34+B35 | D35: =ROUND(D34*(1-B10)+B35*(1-B7),0) | E35: =ROUND(E34*(1-B9)+G35,0) | F35: =D35+E35 | G35: =ROUND(B35*B7+D34*0.005,0) | H35: =ROUND(E35*B8*(1+B11)^(INT((16-1)/12)),2) | I35: =ROUND(H35*B12,2) | J35: =H35-I35 | K35: =ROUND(B13*(1+F35/10000*0.5),2) | L35: =B14 | M35: =ROUND(B35*(1-B16)*B15,2) | N35: =K35+L35+M35 | O35: =J35-N35 | P35: =P34+O35 | Q35: =IF(F35>0,ROUND(J35/F35,2),0) | R35: =IF(B9>0,ROUND(B8*(1-B12)/B9*(1+B11)^(INT((16-1)/12)),2),0) | S35: =IF(F35>0,E35/F35,0)
A36: 17 | B36: =ROUND(B4*(1+B5-B6*17)^(17-1),0) | C36: =C35+B36 | D36: =ROUND(D35*(1-B10)+B36*(1-B7),0) | E36: =ROUND(E35*(1-B9)+G36,0) | F36: =D36+E36 | G36: =ROUND(B36*B7+D35*0.005,0) | H36: =ROUND(E36*B8*(1+B11)^(INT((17-1)/12)),2) | I36: =ROUND(H36*B12,2) | J36: =H36-I36 | K36: =ROUND(B13*(1+F36/10000*0.5),2) | L36: =B14 | M36: =ROUND(B36*(1-B16)*B15,2) | N36: =K36+L36+M36 | O36: =J36-N36 | P36: =P35+O36 | Q36: =IF(F36>0,ROUND(J36/F36,2),0) | R36: =IF(B9>0,ROUND(B8*(1-B12)/B9*(1+B11)^(INT((17-1)/12)),2),0) | S36: =IF(F36>0,E36/F36,0)
A37: 18 | B37: =ROUND(B4*(1+B5-B6*18)^(18-1),0) | C37: =C36+B37 | D37: =ROUND(D36*(1-B10)+B37*(1-B7),0) | E37: =ROUND(E36*(1-B9)+G37,0) | F37: =D37+E37 | G37: =ROUND(B37*B7+D36*0.005,0) | H37: =ROUND(E37*B8*(1+B11)^(INT((18-1)/12)),2) | I37: =ROUND(H37*B12,2) | J37: =H37-I37 | K37: =ROUND(B13*(1+F37/10000*0.5),2) | L37: =B14 | M37: =ROUND(B37*(1-B16)*B15,2) | N37: =K37+L37+M37 | O37: =J37-N37 | P37: =P36+O37 | Q37: =IF(F37>0,ROUND(J37/F37,2),0) | R37: =IF(B9>0,ROUND(B8*(1-B12)/B9*(1+B11)^(INT((18-1)/12)),2),0) | S37: =IF(F37>0,E37/F37,0)
A38: 19 | B38: =ROUND(B4*(1+B5-B6*19)^(19-1),0) | C38: =C37+B38 | D38: =ROUND(D37*(1-B10)+B38*(1-B7),0) | E38: =ROUND(E37*(1-B9)+G38,0) | F38: =D38+E38 | G38: =ROUND(B38*B7+D37*0.005,0) | H38: =ROUND(E38*B8*(1+B11)^(INT((19-1)/12)),2) | I38: =ROUND(H38*B12,2) | J38: =H38-I38 | K38: =ROUND(B13*(1+F38/10000*0.5),2) | L38: =B14 | M38: =ROUND(B38*(1-B16)*B15,2) | N38: =K38+L38+M38 | O38: =J38-N38 | P38: =P37+O38 | Q38: =IF(F38>0,ROUND(J38/F38,2),0) | R38: =IF(B9>0,ROUND(B8*(1-B12)/B9*(1+B11)^(INT((19-1)/12)),2),0) | S38: =IF(F38>0,E38/F38,0)
A39: 20 | B39: =ROUND(B4*(1+B5-B6*20)^(20-1),0) | C39: =C38+B39 | D39: =ROUND(D38*(1-B10)+B39*(1-B7),0) | E39: =ROUND(E38*(1-B9)+G39,0) | F39: =D39+E39 | G39: =ROUND(B39*B7+D38*0.005,0) | H39: =ROUND(E39*B8*(1+B11)^(INT((20-1)/12)),2) | I39: =ROUND(H39*B12,2) | J39: =H39-I39 | K39: =ROUND(B13*(1+F39/10000*0.5),2) | L39: =B14 | M39: =ROUND(B39*(1-B16)*B15,2) | N39: =K39+L39+M39 | O39: =J39-N39 | P39: =P38+O39 | Q39: =IF(F39>0,ROUND(J39/F39,2),0) | R39: =IF(B9>0,ROUND(B8*(1-B12)/B9*(1+B11)^(INT((20-1)/12)),2),0) | S39: =IF(F39>0,E39/F39,0)
A40: 21 | B40: =ROUND(B4*(1+B5-B6*21)^(21-1),0) | C40: =C39+B40 | D40: =ROUND(D39*(1-B10)+B40*(1-B7),0) | E40: =ROUND(E39*(1-B9)+G40,0) | F40: =D40+E40 | G40: =ROUND(B40*B7+D39*0.005,0) | H40: =ROUND(E40*B8*(1+B11)^(INT((21-1)/12)),2) | I40: =ROUND(H40*B12,2) | J40: =H40-I40 | K40: =ROUND(B13*(1+F40/10000*0.5),2) | L40: =B14 | M40: =ROUND(B40*(1-B16)*B15,2) | N40: =K40+L40+M40 | O40: =J40-N40 | P40: =P39+O40 | Q40: =IF(F40>0,ROUND(J40/F40,2),0) | R40: =IF(B9>0,ROUND(B8*(1-B12)/B9*(1+B11)^(INT((21-1)/12)),2),0) | S40: =IF(F40>0,E40/F40,0)
A41: 22 | B41: =ROUND(B4*(1+B5-B6*22)^(22-1),0) | C41: =C40+B41 | D41: =ROUND(D40*(1-B10)+B41*(1-B7),0) | E41: =ROUND(E40*(1-B9)+G41,0) | F41: =D41+E41 | G41: =ROUND(B41*B7+D40*0.005,0) | H41: =ROUND(E41*B8*(1+B11)^(INT((22-1)/12)),2) | I41: =ROUND(H41*B12,2) | J41: =H41-I41 | K41: =ROUND(B13*(1+F41/10000*0.5),2) | L41: =B14 | M41: =ROUND(B41*(1-B16)*B15,2) | N41: =K41+L41+M41 | O41: =J41-N41 | P41: =P40+O41 | Q41: =IF(F41>0,ROUND(J41/F41,2),0) | R41: =IF(B9>0,ROUND(B8*(1-B12)/B9*(1+B11)^(INT((22-1)/12)),2),0) | S41: =IF(F41>0,E41/F41,0)
A42: 23 | B42: =ROUND(B4*(1+B5-B6*23)^(23-1),0) | C42: =C41+B42 | D42: =ROUND(D41*(1-B10)+B42*(1-B7),0) | E42: =ROUND(E41*(1-B9)+G42,0) | F42: =D42+E42 | G42: =ROUND(B42*B7+D41*0.005,0) | H42: =ROUND(E42*B8*(1+B11)^(INT((23-1)/12)),2) | I42: =ROUND(H42*B12,2) | J42: =H42-I42 | K42: =ROUND(B13*(1+F42/10000*0.5),2) | L42: =B14 | M42: =ROUND(B42*(1-B16)*B15,2) | N42: =K42+L42+M42 | O42: =J42-N42 | P42: =P41+O42 | Q42: =IF(F42>0,ROUND(J42/F42,2),0) | R42: =IF(B9>0,ROUND(B8*(1-B12)/B9*(1+B11)^(INT((23-1)/12)),2),0) | S42: =IF(F42>0,E42/F42,0)
A43: 24 | B43: =ROUND(B4*(1+B5-B6*24)^(24-1),0) | C43: =C42+B43 | D43: =ROUND(D42*(1-B10)+B43*(1-B7),0) | E43: =ROUND(E42*(1-B9)+G43,0) | F43: =D43+E43 | G43: =ROUND(B43*B7+D42*0.005,0) | H43: =ROUND(E43*B8*(1+B11)^(INT((24-1)/12)),2) | I43: =ROUND(H43*B12,2) | J43: =H43-I43 | K43: =ROUND(B13*(1+F43/10000*0.5),2) | L43: =B14 | M43: =ROUND(B43*(1-B16)*B15,2) | N43: =K43+L43+M43 | O43: =J43-N43 | P43: =P42+O43 | Q43: =IF(F43>0,ROUND(J43/F43,2),0) | R43: =IF(B9>0,ROUND(B8*(1-B12)/B9*(1+B11)^(INT((24-1)/12)),2),0) | S43: =IF(F43>0,E43/F43,0)
A44: 25 | B44: =ROUND(B4*(1+B5-B6*25)^(25-1),0) | C44: =C43+B44 | D44: =ROUND(D43*(1-B10)+B44*(1-B7),0) | E44: =ROUND(E43*(1-B9)+G44,0) | F44: =D44+E44 | G44: =ROUND(B44*B7+D43*0.005,0) | H44: =ROUND(E44*B8*(1+B11)^(INT((25-1)/12)),2) | I44: =ROUND(H44*B12,2) | J44: =H44-I44 | K44: =ROUND(B13*(1+F44/10000*0.5),2) | L44: =B14 | M44: =ROUND(B44*(1-B16)*B15,2) | N44: =K44+L44+M44 | O44: =J44-N44 | P44: =P43+O44 | Q44: =IF(F44>0,ROUND(J44/F44,2),0) | R44: =IF(B9>0,ROUND(B8*(1-B12)/B9*(1+B11)^(INT((25-1)/12)),2),0) | S44: =IF(F44>0,E44/F44,0)
A45: 26 | B45: =ROUND(B4*(1+B5-B6*26)^(26-1),0) | C45: =C44+B45 | D45: =ROUND(D44*(1-B10)+B45*(1-B7),0) | E45: =ROUND(E44*(1-B9)+G45,0) | F45: =D45+E45 | G45: =ROUND(B45*B7+D44*0.005,0) | H45: =ROUND(E45*B8*(1+B11)^(INT((26-1)/12)),2) | I45: =ROUND(H45*B12,2) | J45: =H45-I45 | K45: =ROUND(B13*(1+F45/10000*0.5),2) | L45: =B14 | M45: =ROUND(B45*(1-B16)*B15,2) | N45: =K45+L45+M45 | O45: =J45-N45 | P45: =P44+O45 | Q45: =IF(F45>0,ROUND(J45/F45,2),0) | R45: =IF(B9>0,ROUND(B8*(1-B12)/B9*(1+B11)^(INT((26-1)/12)),2),0) | S45: =IF(F45>0,E45/F45,0)
A46: 27 | B46: =ROUND(B4*(1+B5-B6*27)^(27-1),0) | C46: =C45+B46 | D46: =ROUND(D45*(1-B10)+B46*(1-B7),0) | E46: =ROUND(E45*(1-B9)+G46,0) | F46: =D46+E46 | G46: =ROUND(B46*B7+D45*0.005,0) | H46: =ROUND(E46*B8*(1+B11)^(INT((27-1)/12)),2) | I46: =ROUND(H46*B12,2) | J46: =H46-I46 | K46: =ROUND(B13*(1+F46/10000*0.5),2) | L46: =B14 | M46: =ROUND(B46*(1-B16)*B15,2) | N46: =K46+L46+M46 | O46: =J46-N46 | P46: =P45+O46 | Q46: =IF(F46>0,ROUND(J46/F46,2),0) | R46: =IF(B9>0,ROUND(B8*(1-B12)/B9*(1+B11)^(INT((27-1)/12)),2),0) | S46: =IF(F46>0,E46/F46,0)
A47: 28 | B47: =ROUND(B4*(1+B5-B6*28)^(28-1),0) | C47: =C46+B47 | D47: =ROUND(D46*(1-B10)+B47*(1-B7),0) | E47: =ROUND(E46*(1-B9)+G47,0) | F47: =D47+E47 | G47: =ROUND(B47*B7+D46*0.005,0) | H47: =ROUND(E47*B8*(1+B11)^(INT((28-1)/12)),2) | I47: =ROUND(H47*B12,2) | J47: =H47-I47 | K47: =ROUND(B13*(1+F47/10000*0.5),2) | L47: =B14 | M47: =ROUND(B47*(1-B16)*B15,2) | N47: =K47+L47+M47 | O47: =J47-N47 | P47: =P46+O47 | Q47: =IF(F47>0,ROUND(J47/F47,2),0) | R47: =IF(B9>0,ROUND(B8*(1-B12)/B9*(1+B11)^(INT((28-1)/12)),2),0) | S47: =IF(F47>0,E47/F47,0)
A48: 29 | B48: =ROUND(B4*(1+B5-B6*29)^(29-1),0) | C48: =C47+B48 | D48: =ROUND(D47*(1-B10)+B48*(1-B7),0) | E48: =ROUND(E47*(1-B9)+G48,0) | F48: =D48+E48 | G48: =ROUND(B48*B7+D47*0.005,0) | H48: =ROUND(E48*B8*(1+B11)^(INT((29-1)/12)),2) | I48: =ROUND(H48*B12,2) | J48: =H48-I48 | K48: =ROUND(B13*(1+F48/10000*0.5),2) | L48: =B14 | M48: =ROUND(B48*(1-B16)*B15,2) | N48: =K48+L48+M48 | O48: =J48-N48 | P48: =P47+O48 | Q48: =IF(F48>0,ROUND(J48/F48,2),0) | R48: =IF(B9>0,ROUND(B8*(1-B12)/B9*(1+B11)^(INT((29-1)/12)),2),0) | S48: =IF(F48>0,E48/F48,0)
A49: 30 | B49: =ROUND(B4*(1+B5-B6*30)^(30-1),0) | C49: =C48+B49 | D49: =ROUND(D48*(1-B10)+B49*(1-B7),0) | E49: =ROUND(E48*(1-B9)+G49,0) | F49: =D49+E49 | G49: =ROUND(B49*B7+D48*0.005,0) | H49: =ROUND(E49*B8*(1+B11)^(INT((30-1)/12)),2) | I49: =ROUND(H49*B12,2) | J49: =H49-I49 | K49: =ROUND(B13*(1+F49/10000*0.5),2) | L49: =B14 | M49: =ROUND(B49*(1-B16)*B15,2) | N49: =K49+L49+M49 | O49: =J49-N49 | P49: =P48+O49 | Q49: =IF(F49>0,ROUND(J49/F49,2),0) | R49: =IF(B9>0,ROUND(B8*(1-B12)/B9*(1+B11)^(INT((30-1)/12)),2),0) | S49: =IF(F49>0,E49/F49,0)
A50: 31 | B50: =ROUND(B4*(1+B5-B6*31)^(31-1),0) | C50: =C49+B50 | D50: =ROUND(D49*(1-B10)+B50*(1-B7),0) | E50: =ROUND(E49*(1-B9)+G50,0) | F50: =D50+E50 | G50: =ROUND(B50*B7+D49*0.005,0) | H50: =ROUND(E50*B8*(1+B11)^(INT((31-1)/12)),2) | I50: =ROUND(H50*B12,2) | J50: =H50-I50 | K50: =ROUND(B13*(1+F50/10000*0.5),2) | L50: =B14 | M50: =ROUND(B50*(1-B16)*B15,2) | N50: =K50+L50+M50 | O50: =J50-N50 | P50: =P49+O50 | Q50: =IF(F50>0,ROUND(J50/F50,2),0) | R50: =IF(B9>0,ROUND(B8*(1-B12)/B9*(1+B11)^(INT((31-1)/12)),2),0) | S50: =IF(F50>0,E50/F50,0)
A51: 32 | B51: =ROUND(B4*(1+B5-B6*32)^(32-1),0) | C51: =C50+B51 | D51: =ROUND(D50*(1-B10)+B51*(1-B7),0) | E51: =ROUND(E50*(1-B9)+G51,0) | F51: =D51+E51 | G51: =ROUND(B51*B7+D50*0.005,0) | H51: =ROUND(E51*B8*(1+B11)^(INT((32-1)/12)),2) | I51: =ROUND(H51*B12,2) | J51: =H51-I51 | K51: =ROUND(B13*(1+F51/10000*0.5),2) | L51: =B14 | M51: =ROUND(B51*(1-B16)*B15,2) | N51: =K51+L51+M51 | O51: =J51-N51 | P51: =P50+O51 | Q51: =IF(F51>0,ROUND(J51/F51,2),0) | R51: =IF(B9>0,ROUND(B8*(1-B12)/B9*(1+B11)^(INT((32-1)/12)),2),0) | S51: =IF(F51>0,E51/F51,0)
A52: 33 | B52: =ROUND(B4*(1+B5-B6*33)^(33-1),0) | C52: =C51+B52 | D52: =ROUND(D51*(1-B10)+B52*(1-B7),0) | E52: =ROUND(E51*(1-B9)+G52,0) | F52: =D52+E52 | G52: =ROUND(B52*B7+D51*0.005,0) | H52: =ROUND(E52*B8*(1+B11)^(INT((33-1)/12)),2) | I52: =ROUND(H52*B12,2) | J52: =H52-I52 | K52: =ROUND(B13*(1+F52/10000*0.5),2) | L52: =B14 | M52: =ROUND(B52*(1-B16)*B15,2) | N52: =K52+L52+M52 | O52: =J52-N52 | P52: =P51+O52 | Q52: =IF(F52>0,ROUND(J52/F52,2),0) | R52: =IF(B9>0,ROUND(B8*(1-B12)/B9*(1+B11)^(INT((33-1)/12)),2),0) | S52: =IF(F52>0,E52/F52,0)
A53: 34 | B53: =ROUND(B4*(1+B5-B6*34)^(34-1),0) | C53: =C52+B53 | D53: =ROUND(D52*(1-B10)+B53*(1-B7),0) | E53: =ROUND(E52*(1-B9)+G53,0) | F53: =D53+E53 | G53: =ROUND(B53*B7+D52*0.005,0) | H53: =ROUND(E53*B8*(1+B11)^(INT((34-1)/12)),2) | I53: =ROUND(H53*B12,2) | J53: =H53-I53 | K53: =ROUND(B13*(1+F53/10000*0.5),2) | L53: =B14 | M53: =ROUND(B53*(1-B16)*B15,2) | N53: =K53+L53+M53 | O53: =J53-N53 | P53: =P52+O53 | Q53: =IF(F53>0,ROUND(J53/F53,2),0) | R53: =IF(B9>0,ROUND(B8*(1-B12)/B9*(1+B11)^(INT((34-1)/12)),2),0) | S53: =IF(F53>0,E53/F53,0)
A54: 35 | B54: =ROUND(B4*(1+B5-B6*35)^(35-1),0) | C54: =C53+B54 | D54: =ROUND(D53*(1-B10)+B54*(1-B7),0) | E54: =ROUND(E53*(1-B9)+G54,0) | F54: =D54+E54 | G54: =ROUND(B54*B7+D53*0.005,0) | H54: =ROUND(E54*B8*(1+B11)^(INT((35-1)/12)),2) | I54: =ROUND(H54*B12,2) | J54: =H54-I54 | K54: =ROUND(B13*(1+F54/10000*0.5),2) | L54: =B14 | M54: =ROUND(B54*(1-B16)*B15,2) | N54: =K54+L54+M54 | O54: =J54-N54 | P54: =P53+O54 | Q54: =IF(F54>0,ROUND(J54/F54,2),0) | R54: =IF(B9>0,ROUND(B8*(1-B12)/B9*(1+B11)^(INT((35-1)/12)),2),0) | S54: =IF(F54>0,E54/F54,0)
A55: 36 | B55: =ROUND(B4*(1+B5-B6*36)^(36-1),0) | C55: =C54+B55 | D55: =ROUND(D54*(1-B10)+B55*(1-B7),0) | E55: =ROUND(E54*(1-B9)+G55,0) | F55: =D55+E55 | G55: =ROUND(B55*B7+D54*0.005,0) | H55: =ROUND(E55*B8*(1+B11)^(INT((36-1)/12)),2) | I55: =ROUND(H55*B12,2) | J55: =H55-I55 | K55: =ROUND(B13*(1+F55/10000*0.5),2) | L55: =B14 | M55: =ROUND(B55*(1-B16)*B15,2) | N55: =K55+L55+M55 | O55: =J55-N55 | P55: =P54+O55 | Q55: =IF(F55>0,ROUND(J55/F55,2),0) | R55: =IF(B9>0,ROUND(B8*(1-B12)/B9*(1+B11)^(INT((36-1)/12)),2),0) | S55: =IF(F55>0,E55/F55,0)
A56: 37 | B56: =ROUND(B4*(1+B5-B6*37)^(37-1),0) | C56: =C55+B56 | D56: =ROUND(D55*(1-B10)+B56*(1-B7),0) | E56: =ROUND(E55*(1-B9)+G56,0) | F56: =D56+E56 | G56: =ROUND(B56*B7+D55*0.005,0) | H56: =ROUND(E56*B8*(1+B11)^(INT((37-1)/12)),2) | I56: =ROUND(H56*B12,2) | J56: =H56-I56 | K56: =ROUND(B13*(1+F56/10000*0.5),2) | L56: =B14 | M56: =ROUND(B56*(1-B16)*B15,2) | N56: =K56+L56+M56 | O56: =J56-N56 | P56: =P55+O56 | Q56: =IF(F56>0,ROUND(J56/F56,2),0) | R56: =IF(B9>0,ROUND(B8*(1-B12)/B9*(1+B11)^(INT((37-1)/12)),2),0) | S56: =IF(F56>0,E56/F56,0)
A57: 38 | B57: =ROUND(B4*(1+B5-B6*38)^(38-1),0) | C57: =C56+B57 | D57: =ROUND(D56*(1-B10)+B57*(1-B7),0) | E57: =ROUND(E56*(1-B9)+G57,0) | F57: =D57+E57 | G57: =ROUND(B57*B7+D56*0.005,0) | H57: =ROUND(E57*B8*(1+B11)^(INT((38-1)/12)),2) | I57: =ROUND(H57*B12,2) | J57: =H57-I57 | K57: =ROUND(B13*(1+F57/10000*0.5),2) | L57: =B14 | M57: =ROUND(B57*(1-B16)*B15,2) | N57: =K57+L57+M57 | O57: =J57-N57 | P57: =P56+O57 | Q57: =IF(F57>0,ROUND(J57/F57,2),0) | R57: =IF(B9>0,ROUND(B8*(1-B12)/B9*(1+B11)^(INT((38-1)/12)),2),0) | S57: =IF(F57>0,E57/F57,0)
A58: 39 | B58: =ROUND(B4*(1+B5-B6*39)^(39-1),0) | C58: =C57+B58 | D58: =ROUND(D57*(1-B10)+B58*(1-B7),0) | E58: =ROUND(E57*(1-B9)+G58,0) | F58: =D58+E58 | G58: =ROUND(B58*B7+D57*0.005,0) | H58: =ROUND(E58*B8*(1+B11)^(INT((39-1)/12)),2) | I58: =ROUND(H58*B12,2) | J58: =H58-I58 | K58: =ROUND(B13*(1+F58/10000*0.5),2) | L58: =B14 | M58: =ROUND(B58*(1-B16)*B15,2) | N58: =K58+L58+M58 | O58: =J58-N58 | P58: =P57+O58 | Q58: =IF(F58>0,ROUND(J58/F58,2),0) | R58: =IF(B9>0,ROUND(B8*(1-B12)/B9*(1+B11)^(INT((39-1)/12)),2),0) | S58: =IF(F58>0,E58/F58,0)
A59: 40 | B59: =ROUND(B4*(1+B5-B6*40)^(40-1),0) | C59: =C58+B59 | D59: =ROUND(D58*(1-B10)+B59*(1-B7),0) | E59: =ROUND(E58*(1-B9)+G59,0) | F59: =D59+E59 | G59: =ROUND(B59*B7+D58*0.005,0) | H59: =ROUND(E59*B8*(1+B11)^(INT((40-1)/12)),2) | I59: =ROUND(H59*B12,2) | J59: =H59-I59 | K59: =ROUND(B13*(1+F59/10000*0.5),2) | L59: =B14 | M59: =ROUND(B59*(1-B16)*B15,2) | N59: =K59+L59+M59 | O59: =J59-N59 | P59: =P58+O59 | Q59: =IF(F59>0,ROUND(J59/F59,2),0) | R59: =IF(B9>0,ROUND(B8*(1-B12)/B9*(1+B11)^(INT((40-1)/12)),2),0) | S59: =IF(F59>0,E59/F59,0)
A60: 41 | B60: =ROUND(B4*(1+B5-B6*41)^(41-1),0) | C60: =C59+B60 | D60: =ROUND(D59*(1-B10)+B60*(1-B7),0) | E60: =ROUND(E59*(1-B9)+G60,0) | F60: =D60+E60 | G60: =ROUND(B60*B7+D59*0.005,0) | H60: =ROUND(E60*B8*(1+B11)^(INT((41-1)/12)),2) | I60: =ROUND(H60*B12,2) | J60: =H60-I60 | K60: =ROUND(B13*(1+F60/10000*0.5),2) | L60: =B14 | M60: =ROUND(B60*(1-B16)*B15,2) | N60: =K60+L60+M60 | O60: =J60-N60 | P60: =P59+O60 | Q60: =IF(F60>0,ROUND(J60/F60,2),0) | R60: =IF(B9>0,ROUND(B8*(1-B12)/B9*(1+B11)^(INT((41-1)/12)),2),0) | S60: =IF(F60>0,E60/F60,0)
A61: 42 | B61: =ROUND(B4*(1+B5-B6*42)^(42-1),0) | C61: =C60+B61 | D61: =ROUND(D60*(1-B10)+B61*(1-B7),0) | E61: =ROUND(E60*(1-B9)+G61,0) | F61: =D61+E61 | G61: =ROUND(B61*B7+D60*0.005,0) | H61: =ROUND(E61*B8*(1+B11)^(INT((42-1)/12)),2) | I61: =ROUND(H61*B12,2) | J61: =H61-I61 | K61: =ROUND(B13*(1+F61/10000*0.5),2) | L61: =B14 | M61: =ROUND(B61*(1-B16)*B15,2) | N61: =K61+L61+M61 | O61: =J61-N61 | P61: =P60+O61 | Q61: =IF(F61>0,ROUND(J61/F61,2),0) | R61: =IF(B9>0,ROUND(B8*(1-B12)/B9*(1+B11)^(INT((42-1)/12)),2),0) | S61: =IF(F61>0,E61/F61,0)
A62: 43 | B62: =ROUND(B4*(1+B5-B6*43)^(43-1),0) | C62: =C61+B62 | D62: =ROUND(D61*(1-B10)+B62*(1-B7),0) | E62: =ROUND(E61*(1-B9)+G62,0) | F62: =D62+E62 | G62: =ROUND(B62*B7+D61*0.005,0) | H62: =ROUND(E62*B8*(1+B11)^(INT((43-1)/12)),2) | I62: =ROUND(H62*B12,2) | J62: =H62-I62 | K62: =ROUND(B13*(1+F62/10000*0.5),2) | L62: =B14 | M62: =ROUND(B62*(1-B16)*B15,2) | N62: =K62+L62+M62 | O62: =J62-N62 | P62: =P61+O62 | Q62: =IF(F62>0,ROUND(J62/F62,2),0) | R62: =IF(B9>0,ROUND(B8*(1-B12)/B9*(1+B11)^(INT((43-1)/12)),2),0) | S62: =IF(F62>0,E62/F62,0)
A63: 44 | B63: =ROUND(B4*(1+B5-B6*44)^(44-1),0) | C63: =C62+B63 | D63: =ROUND(D62*(1-B10)+B63*(1-B7),0) | E63: =ROUND(E62*(1-B9)+G63,0) | F63: =D63+E63 | G63: =ROUND(B63*B7+D62*0.005,0) | H63: =ROUND(E63*B8*(1+B11)^(INT((44-1)/12)),2) | I63: =ROUND(H63*B12,2) | J63: =H63-I63 | K63: =ROUND(B13*(1+F63/10000*0.5),2) | L63: =B14 | M63: =ROUND(B63*(1-B16)*B15,2) | N63: =K63+L63+M63 | O63: =J63-N63 | P63: =P62+O63 | Q63: =IF(F63>0,ROUND(J63/F63,2),0) | R63: =IF(B9>0,ROUND(B8*(1-B12)/B9*(1+B11)^(INT((44-1)/12)),2),0) | S63: =IF(F63>0,E63/F63,0)
A64: 45 | B64: =ROUND(B4*(1+B5-B6*45)^(45-1),0) | C64: =C63+B64 | D64: =ROUND(D63*(1-B10)+B64*(1-B7),0) | E64: =ROUND(E63*(1-B9)+G64,0) | F64: =D64+E64 | G64: =ROUND(B64*B7+D63*0.005,0) | H64: =ROUND(E64*B8*(1+B11)^(INT((45-1)/12)),2) | I64: =ROUND(H64*B12,2) | J64: =H64-I64 | K64: =ROUND(B13*(1+F64/10000*0.5),2) | L64: =B14 | M64: =ROUND(B64*(1-B16)*B15,2) | N64: =K64+L64+M64 | O64: =J64-N64 | P64: =P63+O64 | Q64: =IF(F64>0,ROUND(J64/F64,2),0) | R64: =IF(B9>0,ROUND(B8*(1-B12)/B9*(1+B11)^(INT((45-1)/12)),2),0) | S64: =IF(F64>0,E64/F64,0)
A65: 46 | B65: =ROUND(B4*(1+B5-B6*46)^(46-1),0) | C65: =C64+B65 | D65: =ROUND(D64*(1-B10)+B65*(1-B7),0) | E65: =ROUND(E64*(1-B9)+G65,0) | F65: =D65+E65 | G65: =ROUND(B65*B7+D64*0.005,0) | H65: =ROUND(E65*B8*(1+B11)^(INT((46-1)/12)),2) | I65: =ROUND(H65*B12,2) | J65: =H65-I65 | K65: =ROUND(B13*(1+F65/10000*0.5),2) | L65: =B14 | M65: =ROUND(B65*(1-B16)*B15,2) | N65: =K65+L65+M65 | O65: =J65-N65 | P65: =P64+O65 | Q65: =IF(F65>0,ROUND(J65/F65,2),0) | R65: =IF(B9>0,ROUND(B8*(1-B12)/B9*(1+B11)^(INT((46-1)/12)),2),0) | S65: =IF(F65>0,E65/F65,0)
A66: 47 | B66: =ROUND(B4*(1+B5-B6*47)^(47-1),0) | C66: =C65+B66 | D66: =ROUND(D65*(1-B10)+B66*(1-B7),0) | E66: =ROUND(E65*(1-B9)+G66,0) | F66: =D66+E66 | G66: =ROUND(B66*B7+D65*0.005,0) | H66: =ROUND(E66*B8*(1+B11)^(INT((47-1)/12)),2) | I66: =ROUND(H66*B12,2) | J66: =H66-I66 | K66: =ROUND(B13*(1+F66/10000*0.5),2) | L66: =B14 | M66: =ROUND(B66*(1-B16)*B15,2) | N66: =K66+L66+M66 | O66: =J66-N66 | P66: =P65+O66 | Q66: =IF(F66>0,ROUND(J66/F66,2),0) | R66: =IF(B9>0,ROUND(B8*(1-B12)/B9*(1+B11)^(INT((47-1)/12)),2),0) | S66: =IF(F66>0,E66/F66,0)
A67: 48 | B67: =ROUND(B4*(1+B5-B6*48)^(48-1),0) | C67: =C66+B67 | D67: =ROUND(D66*(1-B10)+B67*(1-B7),0) | E67: =ROUND(E66*(1-B9)+G67,0) | F67: =D67+E67 | G67: =ROUND(B67*B7+D66*0.005,0) | H67: =ROUND(E67*B8*(1+B11)^(INT((48-1)/12)),2) | I67: =ROUND(H67*B12,2) | J67: =H67-I67 | K67: =ROUND(B13*(1+F67/10000*0.5),2) | L67: =B14 | M67: =ROUND(B67*(1-B16)*B15,2) | N67: =K67+L67+M67 | O67: =J67-N67 | P67: =P66+O67 | Q67: =IF(F67>0,ROUND(J67/F67,2),0) | R67: =IF(B9>0,ROUND(B8*(1-B12)/B9*(1+B11)^(INT((48-1)/12)),2),0) | S67: =IF(F67>0,E67/F67,0)
A68: 49 | B68: =ROUND(B4*(1+B5-B6*49)^(49-1),0) | C68: =C67+B68 | D68: =ROUND(D67*(1-B10)+B68*(1-B7),0) | E68: =ROUND(E67*(1-B9)+G68,0) | F68: =D68+E68 | G68: =ROUND(B68*B7+D67*0.005,0) | H68: =ROUND(E68*B8*(1+B11)^(INT((49-1)/12)),2) | I68: =ROUND(H68*B12,2) | J68: =H68-I68 | K68: =ROUND(B13*(1+F68/10000*0.5),2) | L68: =B14 | M68: =ROUND(B68*(1-B16)*B15,2) | N68: =K68+L68+M68 | O68: =J68-N68 | P68: =P67+O68 | Q68: =IF(F68>0,ROUND(J68/F68,2),0) | R68: =IF(B9>0,ROUND(B8*(1-B12)/B9*(1+B11)^(INT((49-1)/12)),2),0) | S68: =IF(F68>0,E68/F68,0)
A69: 50 | B69: =ROUND(B4*(1+B5-B6*50)^(50-1),0) | C69: =C68+B69 | D69: =ROUND(D68*(1-B10)+B69*(1-B7),0) | E69: =ROUND(E68*(1-B9)+G69,0) | F69: =D69+E69 | G69: =ROUND(B69*B7+D68*0.005,0) | H69: =ROUND(E69*B8*(1+B11)^(INT((50-1)/12)),2) | I69: =ROUND(H69*B12,2) | J69: =H69-I69 | K69: =ROUND(B13*(1+F69/10000*0.5),2) | L69: =B14 | M69: =ROUND(B69*(1-B16)*B15,2) | N69: =K69+L69+M69 | O69: =J69-N69 | P69: =P68+O69 | Q69: =IF(F69>0,ROUND(J69/F69,2),0) | R69: =IF(B9>0,ROUND(B8*(1-B12)/B9*(1+B11)^(INT((50-1)/12)),2),0) | S69: =IF(F69>0,E69/F69,0)
A70: 51 | B70: =ROUND(B4*(1+B5-B6*51)^(51-1),0) | C70: =C69+B70 | D70: =ROUND(D69*(1-B10)+B70*(1-B7),0) | E70: =ROUND(E69*(1-B9)+G70,0) | F70: =D70+E70 | G70: =ROUND(B70*B7+D69*0.005,0) | H70: =ROUND(E70*B8*(1+B11)^(INT((51-1)/12)),2) | I70: =ROUND(H70*B12,2) | J70: =H70-I70 | K70: =ROUND(B13*(1+F70/10000*0.5),2) | L70: =B14 | M70: =ROUND(B70*(1-B16)*B15,2) | N70: =K70+L70+M70 | O70: =J70-N70 | P70: =P69+O70 | Q70: =IF(F70>0,ROUND(J70/F70,2),0) | R70: =IF(B9>0,ROUND(B8*(1-B12)/B9*(1+B11)^(INT((51-1)/12)),2),0) | S70: =IF(F70>0,E70/F70,0)
A71: 52 | B71: =ROUND(B4*(1+B5-B6*52)^(52-1),0) | C71: =C70+B71 | D71: =ROUND(D70*(1-B10)+B71*(1-B7),0) | E71: =ROUND(E70*(1-B9)+G71,0) | F71: =D71+E71 | G71: =ROUND(B71*B7+D70*0.005,0) | H71: =ROUND(E71*B8*(1+B11)^(INT((52-1)/12)),2) | I71: =ROUND(H71*B12,2) | J71: =H71-I71 | K71: =ROUND(B13*(1+F71/10000*0.5),2) | L71: =B14 | M71: =ROUND(B71*(1-B16)*B15,2) | N71: =K71+L71+M71 | O71: =J71-N71 | P71: =P70+O71 | Q71: =IF(F71>0,ROUND(J71/F71,2),0) | R71: =IF(B9>0,ROUND(B8*(1-B12)/B9*(1+B11)^(INT((52-1)/12)),2),0) | S71: =IF(F71>0,E71/F71,0)
A72: 53 | B72: =ROUND(B4*(1+B5-B6*53)^(53-1),0) | C72: =C71+B72 | D72: =ROUND(D71*(1-B10)+B72*(1-B7),0) | E72: =ROUND(E71*(1-B9)+G72,0) | F72: =D72+E72 | G72: =ROUND(B72*B7+D71*0.005,0) | H72: =ROUND(E72*B8*(1+B11)^(INT((53-1)/12)),2) | I72: =ROUND(H72*B12,2) | J72: =H72-I72 | K72: =ROUND(B13*(1+F72/10000*0.5),2) | L72: =B14 | M72: =ROUND(B72*(1-B16)*B15,2) | N72: =K72+L72+M72 | O72: =J72-N72 | P72: =P71+O72 | Q72: =IF(F72>0,ROUND(J72/F72,2),0) | R72: =IF(B9>0,ROUND(B8*(1-B12)/B9*(1+B11)^(INT((53-1)/12)),2),0) | S72: =IF(F72>0,E72/F72,0)
A73: 54 | B73: =ROUND(B4*(1+B5-B6*54)^(54-1),0) | C73: =C72+B73 | D73: =ROUND(D72*(1-B10)+B73*(1-B7),0) | E73: =ROUND(E72*(1-B9)+G73,0) | F73: =D73+E73 | G73: =ROUND(B73*B7+D72*0.005,0) | H73: =ROUND(E73*B8*(1+B11)^(INT((54-1)/12)),2) | I73: =ROUND(H73*B12,2) | J73: =H73-I73 | K73: =ROUND(B13*(1+F73/10000*0.5),2) | L73: =B14 | M73: =ROUND(B73*(1-B16)*B15,2) | N73: =K73+L73+M73 | O73: =J73-N73 | P73: =P72+O73 | Q73: =IF(F73>0,ROUND(J73/F73,2),0) | R73: =IF(B9>0,ROUND(B8*(1-B12)/B9*(1+B11)^(INT((54-1)/12)),2),0) | S73: =IF(F73>0,E73/F73,0)
A74: 55 | B74: =ROUND(B4*(1+B5-B6*55)^(55-1),0) | C74: =C73+B74 | D74: =ROUND(D73*(1-B10)+B74*(1-B7),0) | E74: =ROUND(E73*(1-B9)+G74,0) | F74: =D74+E74 | G74: =ROUND(B74*B7+D73*0.005,0) | H74: =ROUND(E74*B8*(1+B11)^(INT((55-1)/12)),2) | I74: =ROUND(H74*B12,2) | J74: =H74-I74 | K74: =ROUND(B13*(1+F74/10000*0.5),2) | L74: =B14 | M74: =ROUND(B74*(1-B16)*B15,2) | N74: =K74+L74+M74 | O74: =J74-N74 | P74: =P73+O74 | Q74: =IF(F74>0,ROUND(J74/F74,2),0) | R74: =IF(B9>0,ROUND(B8*(1-B12)/B9*(1+B11)^(INT((55-1)/12)),2),0) | S74: =IF(F74>0,E74/F74,0)
A75: 56 | B75: =ROUND(B4*(1+B5-B6*56)^(56-1),0) | C75: =C74+B75 | D75: =ROUND(D74*(1-B10)+B75*(1-B7),0) | E75: =ROUND(E74*(1-B9)+G75,0) | F75: =D75+E75 | G75: =ROUND(B75*B7+D74*0.005,0) | H75: =ROUND(E75*B8*(1+B11)^(INT((56-1)/12)),2) | I75: =ROUND(H75*B12,2) | J75: =H75-I75 | K75: =ROUND(B13*(1+F75/10000*0.5),2) | L75: =B14 | M75: =ROUND(B75*(1-B16)*B15,2) | N75: =K75+L75+M75 | O75: =J75-N75 | P75: =P74+O75 | Q75: =IF(F75>0,ROUND(J75/F75,2),0) | R75: =IF(B9>0,ROUND(B8*(1-B12)/B9*(1+B11)^(INT((56-1)/12)),2),0) | S75: =IF(F75>0,E75/F75,0)
A76: 57 | B76: =ROUND(B4*(1+B5-B6*57)^(57-1),0) | C76: =C75+B76 | D76: =ROUND(D75*(1-B10)+B76*(1-B7),0) | E76: =ROUND(E75*(1-B9)+G76,0) | F76: =D76+E76 | G76: =ROUND(B76*B7+D75*0.005,0) | H76: =ROUND(E76*B8*(1+B11)^(INT((57-1)/12)),2) | I76: =ROUND(H76*B12,2) | J76: =H76-I76 | K76: =ROUND(B13*(1+F76/10000*0.5),2) | L76: =B14 | M76: =ROUND(B76*(1-B16)*B15,2) | N76: =K76+L76+M76 | O76: =J76-N76 | P76: =P75+O76 | Q76: =IF(F76>0,ROUND(J76/F76,2),0) | R76: =IF(B9>0,ROUND(B8*(1-B12)/B9*(1+B11)^(INT((57-1)/12)),2),0) | S76: =IF(F76>0,E76/F76,0)
A77: 58 | B77: =ROUND(B4*(1+B5-B6*58)^(58-1),0) | C77: =C76+B77 | D77: =ROUND(D76*(1-B10)+B77*(1-B7),0) | E77: =ROUND(E76*(1-B9)+G77,0) | F77: =D77+E77 | G77: =ROUND(B77*B7+D76*0.005,0) | H77: =ROUND(E77*B8*(1+B11)^(INT((58-1)/12)),2) | I77: =ROUND(H77*B12,2) | J77: =H77-I77 | K77: =ROUND(B13*(1+F77/10000*0.5),2) | L77: =B14 | M77: =ROUND(B77*(1-B16)*B15,2) | N77: =K77+L77+M77 | O77: =J77-N77 | P77: =P76+O77 | Q77: =IF(F77>0,ROUND(J77/F77,2),0) | R77: =IF(B9>0,ROUND(B8*(1-B12)/B9*(1+B11)^(INT((58-1)/12)),2),0) | S77: =IF(F77>0,E77/F77,0)
A78: 59 | B78: =ROUND(B4*(1+B5-B6*59)^(59-1),0) | C78: =C77+B78 | D78: =ROUND(D77*(1-B10)+B78*(1-B7),0) | E78: =ROUND(E77*(1-B9)+G78,0) | F78: =D78+E78 | G78: =ROUND(B78*B7+D77*0.005,0) | H78: =ROUND(E78*B8*(1+B11)^(INT((59-1)/12)),2) | I78: =ROUND(H78*B12,2) | J78: =H78-I78 | K78: =ROUND(B13*(1+F78/10000*0.5),2) | L78: =B14 | M78: =ROUND(B78*(1-B16)*B15,2) | N78: =K78+L78+M78 | O78: =J78-N78 | P78: =P77+O78 | Q78: =IF(F78>0,ROUND(J78/F78,2),0) | R78: =IF(B9>0,ROUND(B8*(1-B12)/B9*(1+B11)^(INT((59-1)/12)),2),0) | S78: =IF(F78>0,E78/F78,0)
A79: 60 | B79: =ROUND(B4*(1+B5-B6*60)^(60-1),0) | C79: =C78+B79 | D79: =ROUND(D78*(1-B10)+B79*(1-B7),0) | E79: =ROUND(E78*(1-B9)+G79,0) | F79: =D79+E79 | G79: =ROUND(B79*B7+D78*0.005,0) | H79: =ROUND(E79*B8*(1+B11)^(INT((60-1)/12)),2) | I79: =ROUND(H79*B12,2) | J79: =H79-I79 | K79: =ROUND(B13*(1+F79/10000*0.5),2) | L79: =B14 | M79: =ROUND(B79*(1-B16)*B15,2) | N79: =K79+L79+M79 | O79: =J79-N79 | P79: =P78+O79 | Q79: =IF(F79>0,ROUND(J79/F79,2),0) | R79: =IF(B9>0,ROUND(B8*(1-B12)/B9*(1+B11)^(INT((60-1)/12)),2),0) | S79: =IF(F79>0,E79/F79,0)
A80: TOTALS | C80: =SUM(C20:C79) | H80: =SUM(H20:H79) | I80: =SUM(I20:I79) | J80: =SUM(J20:J79) | K80: =SUM(K20:K79) | L80: =SUM(L20:L79) | M80: =SUM(M20:M79) | N80: =SUM(N20:N79) | O80: =SUM(O20:O79)

Sheet Revenue Streams
A1: REVENUE BREAKDOWN BY STREAM — QUARTERLY PROJECTIONS
A3: REVENUE MIX ASSUMPTIONS (% of Gross Revenue)
A4: Revenue Stream | B4: Year 1 Mix | C4: Year 2 Mix | D4: Year 3 Mix | E4: Year 4 Mix | F4: Year 5 Mix | G4: Avg. Transaction | H4: Notes
A5: Coin Pack — Starter ($0.99) | B5: 0.15 | C5: 0.1 | D5: 0.08 | E5: 0.06 | F5: 0.05 | G5: 0.99 | H5: Entry-level, high volume
A6: Coin Pack — Popular ($4.99) | B6: 0.25 | C6: 0.22 | D6: 0.2 | E6: 0.18 | F6: 0.15 | G6: 4.99 | H6: Best value perception
A7: Coin Pack — Big Spender ($9.99) | B7: 0.15 | C7: 0.18 | D7: 0.18 | E7: 0.17 | F7: 0.15 | G7: 9.99 | H7: Mid-tier spenders
A8: Coin Pack — Whale ($24.99) | B8: 0.05 | C8: 0.08 | D8: 0.1 | E8: 0.12 | F8: 0.15 | G8: 24.99 | H8: Whale segment grows
A9: Season Pass — Premium ($9.99) | B9: 0.25 | C9: 0.22 | D9: 0.2 | E9: 0.2 | F9: 0.18 | G9: 9.99 | H9: Core recurring
A10: Season Pass — Plus ($24.99) | B10: 0.1 | C10: 0.12 | D10: 0.14 | E10: 0.15 | F10: 0.17 | G10: 24.99 | H10: Premium recurring
A11: Cosmetics/Skins (Future) | B11: 0 | C11: 0.05 | D11: 0.07 | E11: 0.08 | F11: 0.1 | G11: 2.99 | H11: Phase C+
A12: Rewarded Ads (Future) | B12: 0.05 | C12: 0.03 | D12: 0.03 | E12: 0.04 | F12: 0.05 | G12: 0.02 | H12: Per impression eCPM
A13: TOTAL | B13: =SUM(B5:B12) | C13: =SUM(C5:C12) | D13: =SUM(D5:D12) | E13: =SUM(E5:E12) | F13: =SUM(F5:F12)
A16: QUARTERLY REVENUE BY STREAM (Estimated)
A17: Quarter | B17: Coin Packs | C17: Season Pass Premium | D17: Season Pass Plus | E17: Cosmetics | F17: Ads | G17: Total Gross | H17: Total Net (after 15% fee)
A18: Q1 Y1 | B18: 450 | C18: 375 | D18: 150 | E18: 0 | F18: 75 | G18: 1050 | H18: 892.5
A19: Q2 Y1 | B19: 900 | C19: 660 | D19: 300 | E19: 0 | F19: 90 | G19: 1950 | H19: 1657.5
A20: Q3 Y1 | B20: 1800 | C20: 1100 | D20: 540 | E20: 0 | F20: 110 | G20: 3550 | H20: 3017.5
A21: Q4 Y1 | B21: 3200 | C21: 1760 | D21: 880 | E21: 0 | F21: 160 | G21: 6000 | H21: 5100
A22: Q1 Y2 | B22: 5000 | C22: 2500 | D22: 1350 | E22: 350 | F22: 200 | G22: 9400 | H22: 7990
A23: Q2 Y2 | B23: 7500 | C23: 3300 | D23: 1800 | E23: 600 | F23: 225 | G23: 13425 | H23: 11411.25
A24: Q3 Y2 | B24: 10500 | C24: 4200 | D24: 2400 | E24: 900 | F24: 315 | G24: 18315 | H24: 15567.75
A25: Q4 Y2 | B25: 14000 | C25: 5040 | D25: 3080 | E25: 1260 | F25: 420 | G25: 23800 | H25: 20230
A26: Q1 Y3 | B26: 17500 | C26: 5600 | D26: 3850 | E26: 1750 | F26: 525 | G26: 29225 | H26: 24841.25
A27: Q2 Y3 | B27: 21000 | C27: 6300 | D27: 4410 | E27: 2100 | F27: 630 | G27: 34440 | H27: 29274
A28: Q3 Y3 | B28: 24500 | C28: 6860 | D28: 4900 | E28: 2450 | F28: 735 | G28: 39445 | H28: 33528.25
A29: Q4 Y3 | B29: 28000 | C29: 7280 | D29: 5320 | E29: 2800 | F29: 840 | G29: 44240 | H29: 37604
... A37: Q4 Y5 | B37: 38000 | C37: 6840 | D37: 4180 | E37: 3800 | F37: 1140 | G37: 53960 | H37: 45866
A38: 5-YEAR TOTAL | B38: =SUM(B18:B37) | C38: =SUM(C18:C37) | D38: =SUM(D18:D37) | E38: =SUM(E18:E37) | F38: =SUM(F18:F37) | G38: =SUM(G18:G37) | H38: =SUM(H18:H37)

Sheet KPIs & Unit Economics
A1: KPIs & UNIT ECONOMICS
A3: KEY BUSINESS METRICS
A4: Metric | B4: Formula | C4: Year 1 | D4: Year 2 | E4: Year 3 | F4: Benchmark
A5: Customer Acquisition Cost (CAC) | B5: Marketing Spend / New Users | C5: $2.00 | D5: $1.80 | E5: $1.50 | F5: $1.50-3.00
A6: Lifetime Value (LTV) — Paying | B6: ARPPU / Churn Rate | C6: $63.75 | D6: $66.94 | E6: $70.28 | F6: $30-80
A7: LTV:CAC Ratio | B7: LTV / CAC | C7: 31.9x | D7: 37.2x | E7: 46.9x | F7: > 3:1 healthy
A8: Monthly ARPU (All Users) | B8: Revenue / Active Users | C8: $0.28 | D8: $0.45 | E8: $0.62 | F8: $0.20-1.00
A9: Monthly ARPPU (Paying) | B9: Revenue / Paying Users | C9: $7.50 | D9: $7.88 | E9: $8.27 | F9: $5-15
A10: Conversion Rate | B10: Paying / Total Users | C10: 4.0% | D10: 4.5% | E10: 5.0% | F10: 2-7%
A11: Day 1 Retention | B11: Users returning Day 1 | C11: 40% | D11: 45% | E11: 48% | F11: 35-50%
A12: Day 7 Retention | B12: Users returning Day 7 | C12: 18% | D12: 22% | E12: 25% | F12: 15-25%
A13: Day 30 Retention | B13: Users returning Day 30 | C13: 8% | D13: 10% | E13: 12% | F13: 5-12%
A14: Paying User Churn | B14: Lost paying users / total paying | C14: 10% | D14: 9% | E14: 8% | F14: 5-12%
A15: Revenue Per Session | B15: Revenue / Total Sessions | C15: $0.03 | D15: $0.05 | E15: $0.07 | F15: $0.02-0.10
... A19: Break-even Month | B19: Cumulative P/L turns positive | C19: Month 8-10 | D19: — | E19: — | F19: 6-18 months
A22: SENSITIVITY ANALYSIS — MONTHLY NET REVENUE AT MONTH 12
A23: Conversion \ ARPPU | B23: $5.00 | C23: $7.50 | D23: $10.00 | E23: $12.50 | F23: $15.00
A24: 2% conversion | B24: 340 | C24: 510 | D24: 680 | E24: 850 | F24: 1020
A25: 3% conversion | B25: 510 | C25: 765 | D25: 1020 | E25: 1275 | F25: 1530
A26: 4% conversion | B26: 680 | C26: 1020 | D26: 1360 | E26: 1700 | F26: 2040
A27: 5% conversion | B27: 850 | C27: 1275 | D27: 1700 | E27: 2125 | F27: 2550
A28: 7% conversion | B28: 1190 | C28: 1785 | D28: 2380 | E28: 2975 | F28: 3570

Sheet Scenario Planner
A1: SCENARIO PLANNER — CONSERVATIVE / BASE / OPTIMISTIC
A3: Metric | B3: Conservative | C3: Base Case | D3: Optimistic | E3: Notes
A4: Launch Installs | B4: 1,000 | C4: 2,000 | D4: 5,000 | E4: Depends on launch marketing
A5: Monthly Growth Rate | B5: 8% | C5: 12% | D5: 20% | E5: Organic + paid growth
A6: Conversion Rate | B6: 2% | C6: 4% | D6: 7% | E6: Industry range for casual games
A7: ARPPU | B7: $5.00 | C7: $7.50 | D7: $12.00 | E7: Based on pricing matrix
A8: Paying Churn | B8: 15% | C8: 10% | D8: 6% | E8: Lower = better retention
A9: Free Churn | B9: 20% | C9: 15% | D9: 10% | E9: Content keeps users engaged
A10: App Store Fee | B10: 30% | C10: 15% | D10: 15% | E10: Small Business Program
A11: Month 6 Active Users | B11: 1,200 | C11: 3,500 | D11: 10,000 | E11: Growth dependent
A12: Month 12 Active Users | B12: 2,500 | C12: 6,000 | D12: 25,000 | E12: Viral potential
A13: Month 12 Monthly Revenue | B13: $250 | C13: $2,550 | D13: $15,750 | E13: Net after fees
A14: Month 24 Monthly Revenue | B14: $600 | C14: $8,000 | D14: $45,000 | E14: At scale
... A20: 5-Year ROI | B20: 50% | C20: 500%+ | D20: 2000%+ | E20: Return on investment

Sheet Milestones & Checklist
A1: MILESTONES & MANAGEMENT CHECKLIST
A3: REVENUE MILESTONES
A4: Milestone | B4: Target | C4: Target Month | D4: Status | E4: Notes
A5: First Paying User | B5: 1 user | C5: Month 1 | E5: Validate pricing
A6: 100 Total Users | B6: 100 | C6: Month 2 | E6: Early traction
A7: $100 Monthly Revenue | B7: $100/mo | C7: Month 3-4 | E7: Proof of concept
A8: 1,000 Total Users | B8: 1,000 | C8: Month 4-6 | E8: Growth validation
A9: $1,000 Monthly Revenue | B9: $1K/mo | C9: Month 6-8 | E9: Sustainability signal
A10: Apple Small Business Program | B10: < $1M annual | C10: Month 1 | E10: Apply immediately — 15% fee
A11: Break-even Month | B11: Cum P/L > 0 | C11: Month 8-10 | E11: Critical milestone
A12: $5,000 Monthly Revenue | B12: $5K/mo | C12: Month 12-18 | E12: Part-time income level
A13: 10,000 Active Users | B13: 10K MAU | C13: Month 12-18 | E13: Community scale
A14: $10,000 Monthly Revenue | B14: $10K/mo | C14: Month 18-24 | E14: Full-time viable
A15: $1M Cumulative Revenue | B15: $1M total | C15: Month 36-48 | E15: Major milestone
A18: MONTHLY MANAGEMENT CHECKLIST
A19: Task | B19: Frequency | C19: Details | D19: Done? | E19: Notes
A20: Review App Store Analytics | B20: Weekly | C20: Downloads, ratings, reviews, crash reports
A21: Check Revenue Dashboard | B21: Daily | C21: IAP revenue, refund rate, chargebacks
A22: Monitor Conversion Funnel | B22: Weekly | C22: Install → Register → First Purchase → Repeat
A23: Update User Cohort Analysis | B23: Monthly | C23: Retention curves by install week
A24: Review Churn Reasons | B24: Monthly | C24: Survey lapsed users, analyze drop-off points
A25: A/B Test Pricing | B25: Quarterly | C25: Test different price points and bundles
A26: Update Financial Model | B26: Monthly | C26: Actuals vs. forecast, adjust projections
A27: Review Season Pass Performance | B27: Per Season | C27: Completion rates, upgrade rates
A28: Competitor Analysis | B28: Quarterly | C28: New entrants, pricing changes, features
A29: Tax & Compliance Review | B29: Quarterly | C29: Sales tax, VAT, app store settlements
A30: Marketing ROI Analysis | B30: Monthly | C30: CAC by channel, ROAS, attribution
A31: User Feedback Review | B31: Weekly | C31: App store reviews, support tickets, social media
... A33: Cash Flow Forecast Update | B33: Monthly | C33: 60-90 day cash runway, payment timing

Sheet Fee Optimizer
A1: APP STORE FEE OPTIMIZATION GUIDE
A3: APPLE APP STORE SMALL BUSINESS PROGRAM
A4: Eligibility | B4: Earn < $1M in annual proceeds across all apps
A5: Commission Rate | B5: 15% (vs. standard 30%)
A6: Savings | B6: 50% reduction in fees
A7: Application | B7: Apply at developer.apple.com/enroll
A8: Renewal | B8: Auto-renews if you stay under $1M
A9: If You Exceed $1M | B9: Standard 30% rate applies for rest of year
A10: Subscriptions | B10: 15% after Year 1 subscriber (regardless of program)
A13: GOOGLE PLAY FEE STRUCTURE
A14: Service Fee Tier 1 | B14: 15% on first $1M of annual revenue
A15: Service Fee Tier 2 | B15: 30% on revenue above $1M
A16: Subscriptions | B16: 15% for all subscription revenue (as of 2022)
A17: Key Advantage | B17: Google's 15% tier applies to ALL developers, no application needed
A18: Media Content | B18: 10% for ebooks, music streaming
A19: Payment | B19: Net-30 payment terms via Google payments
A22: FEE SAVINGS CALCULATOR — 15% vs 30%
A23: Annual Gross Revenue | B23: At 30% Fee | C23: At 15% Fee | D23: You Keep (30%) | E23: You Keep (15%) | F23: Annual Savings
A24: 5000 | B24: 1500 | C24: 750 | D24: 3500 | E24: 4250 | F24: 750
A25: 10000 | B25: 3000 | C25: 1500 | D25: 7000 | E25: 8500 | F25: 1500
A26: 25000 | B26: 7500 | C26: 3750 | D26: 17500 | E26: 21250 | F26: 3750
A27: 50000 | B27: 15000 | C27: 7500 | D27: 35000 | E27: 42500 | F27: 7500
A28: 100000 | B28: 30000 | C28: 15000 | D28: 70000 | E28: 85000 | F28: 15000
A29: 250000 | B29: 75000 | C29: 37500 | D29: 175000 | E29: 212500 | F29: 37500
A30: 500000 | B30: 150000 | C30: 75000 | D30: 350000 | E30: 425000 | F30: 75000
A31: 750000 | B31: 225000 | C31: 112500 | D31: 525000 | E31: 637500 | F31: 112500
A32: 1000000 | B32: 300000 | C32: 150000 | D32: 700000 | E32: 850000 | F32: 150000

Sheet Charts
A1: Month | B1: Free Users | C1: Paying Users | D1: Total Active | E1: Gross Revenue | F1: Net Revenue | G1: Net Profit/Loss | H1: Cumulative P/L | I1: New Installs
A2: 1 | B2: ='60-Month Forecast'!D20 | C2: ='60-Month Forecast'!E20 | D2: ='60-Month Forecast'!F20 | E2: ='60-Month Forecast'!H20 | F2: ='60-Month Forecast'!J20 | G2: ='60-Month Forecast'!O20 | H2: ='60-Month Forecast'!P20 | I2: ='60-Month Forecast'!B20
A3: 2 | B3: ='60-Month Forecast'!D21 | C3: ='60-Month Forecast'!E21 | D3: ='60-Month Forecast'!F21 | E3: ='60-Month Forecast'!H21 | F3: ='60-Month Forecast'!J21 | G3: ='60-Month Forecast'!O21 | H3: ='60-Month Forecast'!P21 | I3: ='60-Month Forecast'!B21
A4: 3 | B4: ='60-Month Forecast'!D22 | C4: ='60-Month Forecast'!E22 | D4: ='60-Month Forecast'!F22 | E4: ='60-Month Forecast'!H22 | F4: ='60-Month Forecast'!J22 | G4: ='60-Month Forecast'!O22 | H4: ='60-Month Forecast'!P22 | I4: ='60-Month Forecast'!B22
A5: 4 | B5: ='60-Month Forecast'!D23 | C5: ='60-Month Forecast'!E23 | D5: ='60-Month Forecast'!F23 | E5: ='60-Month Forecast'!H23 | F5: ='60-Month Forecast'!J23 | G5: ='60-Month Forecast'!O23 | H5: ='60-Month Forecast'!P23 | I5: ='60-Month Forecast'!B23
A6: 5 | B6: ='60-Month Forecast'!D24 | C6: ='60-Month Forecast'!E24 | D6: ='60-Month Forecast'!F24 | E6: ='60-Month Forecast'!H24 | F6: ='60-Month Forecast'!J24 | G6: ='60-Month Forecast'!O24 | H6: ='60-Month Forecast'!P24 | I6: ='60-Month Forecast'!B24
A7: 6 | B7: ='60-Month Forecast'!D25 | C7: ='60-Month Forecast'!E25 | D7: ='60-Month Forecast'!F25 | E7: ='60-Month Forecast'!H25 | F7: ='60-Month Forecast'!J25 | G7: ='60-Month Forecast'!O25 | H7: ='60-Month Forecast'!P25 | I7: ='60-Month Forecast'!B25
A8: 7 | B8: ='60-Month Forecast'!D26 | C8: ='60-Month Forecast'!E26 | D8: ='60-Month Forecast'!F26 | E8: ='60-Month Forecast'!H26 | F8: ='60-Month Forecast'!J26 | G8: ='60-Month Forecast'!O26 | H8: ='60-Month Forecast'!P26 | I8: ='60-Month Forecast'!B26
A9: 8 | B9: ='60-Month Forecast'!D27 | C9: ='60-Month Forecast'!E27 | D9: ='60-Month Forecast'!F27 | E9: ='60-Month Forecast'!H27 | F9: ='60-Month Forecast'!J27 | G9: ='60-Month Forecast'!O27 | H9: ='60-Month Forecast'!P27 | I9: ='60-Month Forecast'!B27
A10: 9 | B10: ='60-Month Forecast'!D28 | C10: ='60-Month Forecast'!E28 | D10: ='60-Month Forecast'!F28 | E10: ='60-Month Forecast'!H28 | F10: ='60-Month Forecast'!J28 | G10: ='60-Month Forecast'!O28 | H10: ='60-Month Forecast'!P28 | I10: ='60-Month Forecast'!B28
A11: 10 | B11: ='60-Month Forecast'!D29 | C11: ='60-Month Forecast'!E29 | D11: ='60-Month Forecast'!F29 | E11: ='60-Month Forecast'!H29 | F11: ='60-Month Forecast'!J29 | G11: ='60-Month Forecast'!O29 | H11: ='60-Month Forecast'!P29 | I11: ='60-Month Forecast'!B29
A12: 11 | B12: ='60-Month Forecast'!D30 | C12: ='60-Month Forecast'!E30 | D12: ='60-Month Forecast'!F30 | E12: ='60-Month Forecast'!H30 | F12: ='60-Month Forecast'!J30 | G12: ='60-Month Forecast'!O30 | H12: ='60-Month Forecast'!P30 | I12: ='60-Month Forecast'!B30
A13: 12 | B13: ='60-Month Forecast'!D31 | C13: ='60-Month Forecast'!E31 | D13: ='60-Month Forecast'!F31 | E13: ='60-Month Forecast'!H31 | F13: ='60-Month Forecast'!J31 | G13: ='60-Month Forecast'!O31 | H13: ='60-Month Forecast'!P31 | I13: ='60-Month Forecast'!B31
... A61: 60 | B61: ='60-Month Forecast'!D79 | C61: ='60-Month Forecast'!E79 | D61: ='60-Month Forecast'!F79 | E61: ='60-Month Forecast'!H79 | F61: ='60-Month Forecast'!J79 | G61: ='60-Month Forecast'!O79 | H61: ='60-Month Forecast'!P79 | I61: ='60-Month Forecast'!B79
